SafeDelete/SafeDelete.py
SafeDelete/__init__.py
SafeDelete-0.0.2.dist-info/LICENSE
SafeDelete-0.0.2.dist-info/METADATA
SafeDelete-0.0.2.dist-info/WHEEL
SafeDelete-0.0.2.dist-info/top_level.txt
SafeDelete-0.0.2.dist-info/RECORD
